genpilot/__init__.py
genpilot/abc/__init__.py
genpilot/abc/agent.py
genpilot/abc/chat.py
genpilot/abc/mcp_agent.py
genpilot/abc/mcp_chat.py
genpilot/abc/memory.py
genpilot/agent/__init__.py
genpilot/agent/default_agent.py
genpilot/chat/__init__.py
genpilot/chat/chainlit_chat.py
genpilot/chat/streamlit_chat.py
genpilot/chat/terminal_chat.py
genpilot/mcp/__init__.py
genpilot/mcp/config.py
genpilot/mcp/manager.py
genpilot/mcp/server.py
genpilot/memory/__init__.py
genpilot/memory/buffer_memory.py
genpilot/tools/__init__.py
genpilot/tools/code_executor.py
genpilot/tools/kubectl_executor.py
genpilot/tools/mcp_toolkit.py
genpilot/tools/tool_validator.py
genpilot/utils/format.py
genpilot/utils/function_to_schema.py
genpilot/utils/mcp_server_config.py
genpilot-0.1.5.dist-info/METADATA
genpilot-0.1.5.dist-info/WHEEL
genpilot-0.1.5.dist-info/RECORD
