Metadata-Version: 2.3
Name: genpilot
Version: 0.1.5
Summary: GenPilot streamlines the creation of multi-agent systems powered by Generative AI. Adhering to the Model Context Protocol (MCP), it ensures seamless integration with MCP servers through an intuitive terminal or web interface
License: MIT
Keywords: agent,MCP,chat,ai,UI
Author: myan
Author-email: myan@redhat.com
Requires-Python: <4.0,>=3.10
Classifier: License :: OSI Approved :: MIT License
Classifier: Programming Language :: Python :: 3
Classifier: Programming Language :: Python :: 3.10
Classifier: Programming Language :: Python :: 3.11
Classifier: Programming Language :: Python :: 3.12
Classifier: Programming Language :: Python :: 3.13
Requires-Dist: chainlit (>=2.2.1,<3.0.0)
Requires-Dist: commentjson (>=0.9.0,<0.10.0)
Requires-Dist: litellm (>=1.61.13,<2.0.0)
Requires-Dist: mcp (>=1.3.0,<2.0.0)
Requires-Dist: openai-agents (>=0.0.4,<0.0.5)
Requires-Dist: rich (>=13.9.4,<14.0.0)
Requires-Dist: streamlit (>=1.42.2,<2.0.0)
Requires-Dist: textual (>=2.1.1,<3.0.0)
Project-URL: Repository, https://github.com/yanmxa/genpilot
